backtrack_sampler/__init__.py
backtrack_sampler/backtrack_sampler.py
backtrack_sampler/provider/__init__.py
backtrack_sampler/provider/base_provider.py
backtrack_sampler/provider/llamacpp_provider.py
backtrack_sampler/provider/transformers_provider.py
backtrack_sampler/strategy/__init__.py
backtrack_sampler/strategy/adaptive_temperature_strategy.py
backtrack_sampler/strategy/antislop_strategy.py
backtrack_sampler/strategy/base_strategy.py
backtrack_sampler/strategy/chain_strategy.py
backtrack_sampler/strategy/creative_writing_strategy.py
backtrack_sampler/strategy/debug_strategy.py
backtrack_sampler/strategy/human_guidance_strategy.py
backtrack_sampler/strategy/replace_strategy.py
backtrack_sampler-3.2.1.dist-info/METADATA
backtrack_sampler-3.2.1.dist-info/WHEEL
backtrack_sampler-3.2.1.dist-info/top_level.txt
backtrack_sampler-3.2.1.dist-info/RECORD
