Metadata-Version: 2.1
Name: backtrack-sampler
Version: 3.2.1
Summary: An easy-to-understand framework for LLM samplers that rewind and revise generated tokens
Home-page: https://github.com/Mihaiii/backtrack_sampler
Author: Mihai Chirculescu
Author-email: apropodemine@gmail.com
License: UNKNOWN
Platform: UNKNOWN
